{
	"configurations" : 
	[
		{
			"directories" : 
			[
				{
					"build" : ".",
					"minimumCMakeVersion" : 
					{
						"string" : "3.19"
					},
					"projectIndex" : 0,
					"source" : ".",
					"targetIndexes" : 
					[
						0
					]
				}
			],
			"name" : "Debug",
			"projects" : 
			[
				{
					"directoryIndexes" : 
					[
						0
					],
					"name" : "repo",
					"targetIndexes" : 
					[
						0
					]
				}
			],
			"targets" : 
			[
				{
					"directoryIndex" : 0,
					"id" : "repo::@6890427a1f51a3e7e1df",
					"jsonFile" : "target-repo-Debug-99869c02efd3320ff028.json",
					"name" : "repo",
					"projectIndex" : 0
				}
			]
		}
	],
	"kind" : "codemodel",
	"paths" : 
	{
		"build" : "C:/Users/tommy/Documents/Polito/System and Device Programming/Project/repo/out/build/x64-Debug",
		"source" : "C:/Users/tommy/Documents/Polito/System and Device Programming/Project/repo"
	},
	"version" : 
	{
		"major" : 2,
		"minor" : 2
	}
}
